automapper/__init__.py
automapper/exceptions.py
automapper/mapper.py
automapper/mapper_initializer.py
automapper/py.typed
automapper/utils.py
automapper/extensions/__init__.py
automapper/extensions/default.py
automapper/extensions/pydantic.py
automapper/extensions/sqlalchemy.py
automapper/extensions/tortoise.py
py_automapper-2.2.0.dist-info/LICENSE
py_automapper-2.2.0.dist-info/METADATA
py_automapper-2.2.0.dist-info/WHEEL
py_automapper-2.2.0.dist-info/top_level.txt
py_automapper-2.2.0.dist-info/RECORD
