Metadata-Version: 2.1
Name: py-automapper
Version: 2.2.0
Summary: Library for automatically mapping one object to another
Author-email: Andrii Nikolaienko <anikolaienko14@gmail.com>
Maintainer-email: Andrii Nikolaienko <anikolaienko14@gmail.com>
License: MIT License
Project-URL: Homepage, https://github.com/anikolaienko/py-automapper
Project-URL: Repository, https://github.com/anikolaienko/py-automapper.git
Project-URL: Issues, https://github.com/anikolaienko/py-automapper/issues
Project-URL: Changelog, https://github.com/anikolaienko/py-automapper/blob/main/CHANGELOG.md
Keywords: utils,dto,object-mapper,mapping,development
Classifier: License :: OSI Approved :: MIT License
Classifier: Development Status :: 5 - Production/Stable
Classifier: Intended Audience :: Developers
Classifier: Programming Language :: Python :: 3
Classifier: Programming Language :: Python :: 3.8
Classifier: Programming Language :: Python :: 3.9
Classifier: Programming Language :: Python :: 3.10
Classifier: Programming Language :: Python :: 3.11
Classifier: Programming Language :: Python :: 3.12
Classifier: Programming Language :: Python :: 3.13
Classifier: Programming Language :: Python :: 3 :: Only
Classifier: Programming Language :: Python :: Implementation :: CPython
Classifier: Programming Language :: Python :: Implementation :: PyPy
Classifier: Topic :: Software Development :: Libraries :: Python Modules
Classifier: Topic :: Software Development :: Build Tools
Requires-Python: >=3.8
License-File: LICENSE
Provides-Extra: dev
Requires-Dist: tortoise-orm ~=0.23.0 ; extra == 'dev'
Requires-Dist: pydantic ~=2.10.6 ; extra == 'dev'
Requires-Dist: SQLAlchemy ~=2.0.38 ; extra == 'dev'
Requires-Dist: twine ~=6.1.0 ; extra == 'dev'
Requires-Dist: Sphinx ~=7.1.2 ; extra == 'dev'
Provides-Extra: test
Requires-Dist: pre-commit ~=3.5.0 ; extra == 'test'
Requires-Dist: pytest ~=8.3.5 ; extra == 'test'
Requires-Dist: pytest-cov ~=5.0.0 ; extra == 'test'
Requires-Dist: mypy ~=1.14.1 ; extra == 'test'
